{"final_epoch": 54, "lr_reduction_epochs": [36, 52], "epoch_logs": [{"epoch": 1, "train_loss": 0.89582352694648, "train_accuracy": 71.672, "val_loss": 0.43599049671541285, "val_accuracy": 86.61, "learning_rate": 0.001}, {"epoch": 2, "train_loss": 0.5237264040943301, "train_accuracy": 83.91, "val_loss": 0.35802676104292086, "val_accuracy": 89.17, "learning_rate": 0.001}, {"epoch": 3, "train_loss": 0.43398704511277814, "train_accuracy": 86.646, "val_loss": 0.3184699055892003, "val_accuracy": 90.1, "learning_rate": 0.001}, {"epoch": 4, "train_loss": 0.38919181092773253, "train_accuracy": 87.896, "val_loss": 0.2800439573541472, "val_accuracy": 91.27, "learning_rate": 0.001}, {"epoch": 5, "train_loss": 0.3592853249262666, "train_accuracy": 88.842, "val_loss": 0.26584368500905703, "val_accuracy": 91.83, "learning_rate": 0.001}, {"epoch": 6, "train_loss": 0.3336165185703341, "train_accuracy": 89.658, "val_loss": 0.25310946595442446, "val_accuracy": 92.4, "learning_rate": 0.001}, {"epoch": 7, "train_loss": 0.31861022240518, "train_accuracy": 90.038, "val_loss": 0.23834628517491907, "val_accuracy": 92.72, "learning_rate": 0.001}, {"epoch": 8, "train_loss": 0.3058010987994616, "train_accuracy": 90.55, "val_loss": 0.23142064541955537, "val_accuracy": 93.12, "learning_rate": 0.001}, {"epoch": 9, "train_loss": 0.28942991667391393, "train_accuracy": 90.962, "val_loss": 0.23318039673038676, "val_accuracy": 92.94, "learning_rate": 0.001}, {"epoch": 10, "train_loss": 0.28461193323821365, "train_accuracy": 91.206, "val_loss": 0.22358321417358856, "val_accuracy": 93.36, "learning_rate": 0.001}, {"epoch": 11, "train_loss": 0.27431063796095834, "train_accuracy": 91.388, "val_loss": 0.22402476934315282, "val_accuracy": 93.47, "learning_rate": 0.001}, {"epoch": 12, "train_loss": 0.2648976236734244, "train_accuracy": 91.666, "val_loss": 0.2175453980512257, "val_accuracy": 93.36, "learning_rate": 0.001}, {"epoch": 13, "train_loss": 0.25829133315159536, "train_accuracy": 91.978, "val_loss": 0.21430495353061943, "val_accuracy": 93.54, "learning_rate": 0.001}, {"epoch": 14, "train_loss": 0.2502401658069447, "train_accuracy": 92.13, "val_loss": 0.2138054085117352, "val_accuracy": 93.63, "learning_rate": 0.001}, {"epoch": 15, "train_loss": 0.24540924839199046, "train_accuracy": 92.25, "val_loss": 0.2088794148515297, "val_accuracy": 93.7, "learning_rate": 0.001}, {"epoch": 16, "train_loss": 0.2430584928987886, "train_accuracy": 92.366, "val_loss": 0.21099313810656342, "val_accuracy": 93.52, "learning_rate": 0.001}, {"epoch": 17, "train_loss": 0.2360516183478448, "train_accuracy": 92.546, "val_loss": 0.21823289603749407, "val_accuracy": 93.5, "learning_rate": 0.001}, {"epoch": 18, "train_loss": 0.22824281396920723, "train_accuracy": 92.764, "val_loss": 0.21661077538811707, "val_accuracy": 93.73, "learning_rate": 0.001}, {"epoch": 19, "train_loss": 0.22875651406586323, "train_accuracy": 92.756, "val_loss": 0.20162863435247277, "val_accuracy": 94.06, "learning_rate": 0.001}, {"epoch": 20, "train_loss": 0.22432261949305035, "train_accuracy": 92.986, "val_loss": 0.20305029142506514, "val_accuracy": 93.81, "learning_rate": 0.001}, {"epoch": 21, "train_loss": 0.21717004708545593, "train_accuracy": 93.2, "val_loss": 0.1985666094512879, "val_accuracy": 94.12, "learning_rate": 0.001}, {"epoch": 22, "train_loss": 0.21710572654710097, "train_accuracy": 93.038, "val_loss": 0.19818903204006486, "val_accuracy": 94.2, "learning_rate": 0.001}, {"epoch": 23, "train_loss": 0.21510727145254155, "train_accuracy": 93.304, "val_loss": 0.197113231437493, "val_accuracy": 94.33, "learning_rate": 0.001}, {"epoch": 24, "train_loss": 0.21167471244588226, "train_accuracy": 93.284, "val_loss": 0.2002392805924144, "val_accuracy": 94.0, "learning_rate": 0.001}, {"epoch": 25, "train_loss": 0.210586340931218, "train_accuracy": 93.472, "val_loss": 0.1963937759305103, "val_accuracy": 94.2, "learning_rate": 0.001}, {"epoch": 26, "train_loss": 0.20831293385961783, "train_accuracy": 93.54, "val_loss": 0.20510073091033137, "val_accuracy": 93.8, "learning_rate": 0.001}, {"epoch": 27, "train_loss": 0.1996086297933098, "train_accuracy": 93.51, "val_loss": 0.19988966968995106, "val_accuracy": 94.14, "learning_rate": 0.001}, {"epoch": 28, "train_loss": 0.19451335385022567, "train_accuracy": 93.796, "val_loss": 0.19584242728409135, "val_accuracy": 94.22, "learning_rate": 0.001}, {"epoch": 29, "train_loss": 0.1966794273908943, "train_accuracy": 93.584, "val_loss": 0.20556520675367948, "val_accuracy": 94.02, "learning_rate": 0.001}, {"epoch": 30, "train_loss": 0.20200426664079546, "train_accuracy": 93.682, "val_loss": 0.1991980750632437, "val_accuracy": 94.22, "learning_rate": 0.001}, {"epoch": 31, "train_loss": 0.1980928886119667, "train_accuracy": 93.638, "val_loss": 0.19861337099271484, "val_accuracy": 94.29, "learning_rate": 0.001}, {"epoch": 32, "train_loss": 0.19098138207059992, "train_accuracy": 94.072, "val_loss": 0.19077435607397103, "val_accuracy": 94.54, "learning_rate": 0.001}, {"epoch": 33, "train_loss": 0.193702142066358, "train_accuracy": 93.884, "val_loss": 0.20315587374417088, "val_accuracy": 94.1, "learning_rate": 0.001}, {"epoch": 34, "train_loss": 0.1917404138275882, "train_accuracy": 93.82, "val_loss": 0.19339308628364454, "val_accuracy": 94.38, "learning_rate": 0.001}, {"epoch": 35, "train_loss": 0.18924357930717567, "train_accuracy": 93.974, "val_loss": 0.19248600667224655, "val_accuracy": 94.21, "learning_rate": 0.001}, {"epoch": 36, "train_loss": 0.18311629018477163, "train_accuracy": 94.2, "val_loss": 0.19297027729357344, "val_accuracy": 94.41, "learning_rate": 0.0001}, {"epoch": 37, "train_loss": 0.1538133648083643, "train_accuracy": 95.134, "val_loss": 0.18520202912107298, "val_accuracy": 94.77, "learning_rate": 0.0001}, {"epoch": 38, "train_loss": 0.14902995603011393, "train_accuracy": 95.26, "val_loss": 0.18448131559770317, "val_accuracy": 94.87, "learning_rate": 0.0001}, {"epoch": 39, "train_loss": 0.14907366140266817, "train_accuracy": 95.236, "val_loss": 0.18264907214177561, "val_accuracy": 94.81, "learning_rate": 0.0001}, {"epoch": 40, "train_loss": 0.14952853052398127, "train_accuracy": 95.146, "val_loss": 0.18287938472496557, "val_accuracy": 94.86, "learning_rate": 0.0001}, {"epoch": 41, "train_loss": 0.14367487907524, "train_accuracy": 95.418, "val_loss": 0.18063900313234027, "val_accuracy": 94.73, "learning_rate": 0.0001}, {"epoch": 42, "train_loss": 0.14643162669008955, "train_accuracy": 95.33, "val_loss": 0.18227454986941966, "val_accuracy": 94.85, "learning_rate": 0.0001}, {"epoch": 43, "train_loss": 0.14322490030732912, "train_accuracy": 95.46, "val_loss": 0.18033911469333533, "val_accuracy": 94.83, "learning_rate": 0.0001}, {"epoch": 44, "train_loss": 0.14322405573352218, "train_accuracy": 95.47, "val_loss": 0.17990106513983087, "val_accuracy": 94.9, "learning_rate": 0.0001}, {"epoch": 45, "train_loss": 0.14326532472811088, "train_accuracy": 95.512, "val_loss": 0.1801970909715076, "val_accuracy": 94.87, "learning_rate": 0.0001}, {"epoch": 46, "train_loss": 0.13657275949845382, "train_accuracy": 95.74, "val_loss": 0.17830728635757784, "val_accuracy": 94.82, "learning_rate": 0.0001}, {"epoch": 47, "train_loss": 0.1410245045905223, "train_accuracy": 95.532, "val_loss": 0.17983177742814715, "val_accuracy": 95.0, "learning_rate": 0.0001}, {"epoch": 48, "train_loss": 0.1396776410415197, "train_accuracy": 95.508, "val_loss": 0.1781006880057386, "val_accuracy": 94.96, "learning_rate": 0.0001}, {"epoch": 49, "train_loss": 0.13865657009736962, "train_accuracy": 95.574, "val_loss": 0.17878850603688368, "val_accuracy": 94.87, "learning_rate": 0.0001}, {"epoch": 50, "train_loss": 0.13863651304865432, "train_accuracy": 95.458, "val_loss": 0.17825054382032987, "val_accuracy": 94.96, "learning_rate": 0.0001}, {"epoch": 51, "train_loss": 0.1374613973967102, "train_accuracy": 95.576, "val_loss": 0.17851381600374663, "val_accuracy": 94.96, "learning_rate": 0.0001}, {"epoch": 52, "train_loss": 0.135155240902701, "train_accuracy": 95.664, "val_loss": 0.17953850394940074, "val_accuracy": 94.94, "learning_rate": 1e-05}, {"epoch": 53, "train_loss": 0.13140959447950049, "train_accuracy": 95.75, "val_loss": 0.1782072092158885, "val_accuracy": 94.96, "learning_rate": 1e-05}]}